README.txt
setup.py
collective/__init__.py
collective.membercriterion.egg-info/PKG-INFO
collective.membercriterion.egg-info/SOURCES.txt
collective.membercriterion.egg-info/dependency_links.txt
collective.membercriterion.egg-info/entry_points.txt
collective.membercriterion.egg-info/namespace_packages.txt
collective.membercriterion.egg-info/not-zip-safe
collective.membercriterion.egg-info/requires.txt
collective.membercriterion.egg-info/top_level.txt
collective/membercriterion/__init__.py
collective/membercriterion/config.py
collective/membercriterion/configure.zcml
collective/membercriterion/memberdata.py
collective/membercriterion/tests.py
collective/membercriterion/vocabulary.py
collective/membercriterion/profiles/default/metadata.xml
collective/membercriterion/profiles/default/portal_atct.xml
collective/membercriterion/profiles/default/types.xml
collective/membercriterion/profiles/default/types/MemberDataCriterion.xml
docs/HISTORY.txt
docs/INSTALL.txt
docs/LICENSE.GPL
docs/LICENSE.txt