Metadata-Version: 1.0
Name: collective.membercriterion
Version: 1.0b3
Summary: An ATContentTypes 'Collection' (aka ATTopic) criterion for comparing content to member properties
Home-page: http://pypi.python.org/pypi/collective.membercriterion
Author: Martin Aspeli
Author-email: optilude@gmail.com
License: GPL
Keywords: Plone collection topic criterion member property
Platform: UNKNOWN
Classifier: Framework :: Plone
Classifier: Programming Language :: Python
Classifier: Topic :: Software Development :: Libraries :: Python Modules
